Metadata-Version: 1.1
Name: micropython-mlx90614
Version: 1.0.0
Summary: MicroPython library for the MLX90614 IR temperature sensor.
Home-page: https://github.com/mcauser/micropython-mlx90614
Author: Mike Causer
Author-email: mcauser@gmail.com
License: MIT
Keywords: mlx90614 infrared temperature micropython
Platform: UNKNOWN
Classifier: Development Status :: 5 - Production/Stable
Classifier: Programming Language :: Python :: Implementation :: MicroPython
Classifier: License :: OSI Approved :: MIT License
